[{"Judul Berita    :": "Pengamat Nilai Peluang Timnas Indonesia U-23 Sama Kuat, Qatar Bukan Tim Istimewa", "Waktu Publish   :": "2 menit yang lalu", "Kategori        :": "Sport", "Waktu Akses     :": "2024-04-15 12:01:56"}, {"Judul Berita    :": "Tol Japek Arah Jakarta Dipadati Kendaraan Arus Balik Pemudik", "Waktu Publish   :": "4 menit yang lalu", "Kategori        :": "Visual", "Waktu Akses     :": "2024-04-15 12:01:56"}, {"Judul Berita    :": "KAI Commuter Wilayah 8 Surabaya Layani Ratusan Ribu Penumpang Selama Libur Lebaran", "Waktu Publish   :": "4 menit yang lalu", "Kategori        :": "News", "Waktu Akses     :": "2024-04-15 12:01:56"}, {"Judul Berita    :": "Reaksi Internasional Terhadap Serangan Iran ke Israel", "Waktu Publish   :": "4 menit yang lalu", "Kategori        :": "Video", "Waktu Akses     :": "2024-04-15 12:01:56"}, {"Judul Berita    :": "Usai Ramadhan, Jusuf Kalla Ajak Umat Islam Tetap Ramaikan Masjid", "Waktu Publish   :": "8 menit yang lalu", "Kategori        :": "News", "Waktu Akses     :": "2024-04-15 12:01:56"}, {"Judul Berita    :": "Shin Tae-yong Sebut Persaingan Grup A Piala Asia U-23 Sangat Kompetitif", "Waktu Publish   :": "11 menit yang lalu", "Kategori        :": "Sport", "Waktu Akses     :": "2024-04-15 12:01:56"}, {"Judul Berita    :": "Prakiraan Cuaca DIY Hari Ini: Hujan Sedang-Lebat, Ada Potensi Angin Kencang", "Waktu Publish   :": "12 menit yang lalu", "Kategori        :": "Rejogja", "Waktu Akses     :": "2024-04-15 12:01:56"}, {"Judul Berita    :": "BPBD DKI: 18 RT di Jaktim Banjir Akibat Luapan Kali Ciliwung", "Waktu Publish   :": "22 menit yang lalu", "Kategori        :": "News", "Waktu Akses     :": "2024-04-15 12:01:56"}, {"Judul Berita    :": "Ini Prediksi Starting XI Timnas Indonesia U-23 Vs Qatar pada Laga Pembuka Piala Asia U-23", "Waktu Publish   :": "22 menit yang lalu", "Kategori        :": "Sport", "Waktu Akses     :": "2024-04-15 12:01:56"}, {"Judul Berita    :": "Wisatawan Pilih Berkemah di Puncak Bogor Habiskan Libur Lebaran", "Waktu Publish   :": "37 menit yang lalu", "Kategori        :": "Ramadhan", "Waktu Akses     :": "2024-04-15 12:01:56"}, {"Judul Berita    :": "Netanyahu Putuskan Tunda Serangan Militer di Rafah", "Waktu Publish   :": "42 menit yang lalu", "Kategori        :": "Internasional", "Waktu Akses     :": "2024-04-15 12:01:56"}, {"Judul Berita    :": "Tampil di Coachella, Le Sserafim Kejutkan Penggemar dengan Lagu Baru", "Waktu Publish   :": "45 menit yang lalu", "Kategori        :": "Ameera", "Waktu Akses     :": "2024-04-15 12:01:56"}, {"Judul Berita    :": "Kemungkinan Gabungnya PDIP ke Koalisi, Idrus Marham: Ada Hitung-Hitungannya", "Waktu Publish   :": "57 menit yang lalu", "Kategori        :": "News", "Waktu Akses     :": "2024-04-15 12:01:56"}, {"Judul Berita    :": "Puncak Arus Balik di Jalur Nagreg Terjadi Ahad Lalu, Ada 143.800 Kendaraan", "Waktu Publish   :": "1 jam yang lalu", "Kategori        :": "Ramadhan", "Waktu Akses     :": "2024-04-15 12:01:56"}, {"Judul Berita    :": "Apa yang Terjadi dalam Gelombang Serangan Iran dan Mengapa Drone Mereka Ditakuti?", "Waktu Publish   :": "1 jam yang lalu", "Kategori        :": "Tekno", "Waktu Akses     :": "2024-04-15 12:01:56"}, {"Judul Berita    :": "Pemda DIY Gelar Griya Lebaran 16 April 2024, Masyarakat Dipersilakan Datang", "Waktu Publish   :": "1 jam yang lalu", "Kategori        :": "Rejogja", "Waktu Akses     :": "2024-04-15 12:01:56"}, {"Judul Berita    :": "Biaya Kuliah IPB Jalur SNBP, SNBT, dan Mandiri 2024, UKT Terendah Rp 500 Ribu", "Waktu Publish   :": "1 jam yang lalu", "Kategori        :": "Network", "Waktu Akses     :": "2024-04-15 12:01:56"}, {"Judul Berita    :": "Alat AI Inovatif Baru Janjikan Revolusi Cara Interpretasi Gambar-Gambar Medis", "Waktu Publish   :": "1 jam yang lalu", "Kategori        :": "Tekno", "Waktu Akses     :": "2024-04-15 12:01:56"}, {"Judul Berita    :": "Polda Lampung Klaim Penanganan Puncak Arus Balik di Bakauheni Terkendali", "Waktu Publish   :": "1 jam yang lalu", "Kategori        :": "Ramadhan", "Waktu Akses     :": "2024-04-15 12:01:56"}, {"Judul Berita    :": "Iran Sebut Hanya Targetkan Situs Militer Israel dalam 'Serangan Terbatas'", "Waktu Publish   :": "2 jam yang lalu", "Kategori        :": "Internasional", "Waktu Akses     :": "2024-04-15 12:01:56"}, {"Judul Berita    :": "Kemenlu Minta WNI Tunda Rencana Perjalanan ke Iran dan Israel", "Waktu Publish   :": "2 jam yang lalu", "Kategori        :": "News", "Waktu Akses     :": "2024-04-15 12:01:56"}, {"Judul Berita    :": "Puan: Kebijakan WFH Bisa Diadopsi Instansi Non-Pemerintah", "Waktu Publish   :": "2 jam yang lalu", "Kategori        :": "Ramadhan", "Waktu Akses     :": "2024-04-15 12:01:56"}, {"Judul Berita    :": "Penggemar Buat Artwork Keanu Reeves dalam Peran Impiannya di Film DC", "Waktu Publish   :": "2 jam yang lalu", "Kategori        :": "Ameera", "Waktu Akses     :": "2024-04-15 12:01:56"}, {"Judul Berita    :": "Atasi Kemacetan, Kendaraan Masuk New York Wajib Bayar", "Waktu Publish   :": "2 jam yang lalu", "Kategori        :": "Video", "Waktu Akses     :": "2024-04-15 12:01:56"}, {"Judul Berita    :": "Seorang Wanita Ditemukan Tewas di Apartemen Jardin Bandung, Diduga Dibunuh", "Waktu Publish   :": "2 jam yang lalu", "Kategori        :": "News", "Waktu Akses     :": "2024-04-15 12:01:56"}, {"Judul Berita    :": "Seberapa Jauh Perang Israel-Iran Berdampak Bagi Indonesia?", "Waktu Publish   :": "2 jam yang lalu", "Kategori        :": "Ekonomi", "Waktu Akses     :": "2024-04-15 12:01:56"}, {"Judul Berita    :": "Kabinet Perang Israel Akhiri Pertemuan Tentang Cara Menanggapi Iran", "Waktu Publish   :": "2 jam yang lalu", "Kategori        :": "Internasional", "Waktu Akses     :": "2024-04-15 12:01:56"}, {"Judul Berita    :": "Jasa Marga Prediksi Puncak Arus Balik di Jalan Tol Terjadi Hari Ini", "Waktu Publish   :": "2 jam yang lalu", "Kategori        :": "Ramadhan", "Waktu Akses     :": "2024-04-15 12:01:56"}, {"Judul Berita    :": "BMKG Ingatkan Hujan Disertai Angin Kencang di Jaksel dan Jaktim Hari Ini", "Waktu Publish   :": "2 jam yang lalu", "Kategori        :": "News", "Waktu Akses     :": "2024-04-15 12:01:56"}, {"Judul Berita    :": "Ini Manfaat Pemblokiran Iklan untuk Cegah Spyware Pemerintah", "Waktu Publish   :": "2 jam yang lalu", "Kategori        :": "Tekno", "Waktu Akses     :": "2024-04-15 12:01:56"}, {"Judul Berita    :": "Seorang Polisi dari Polda Banten Meninggal Saat Pengamanan Wisata di Anyer", "Waktu Publish   :": "3 jam yang lalu", "Kategori        :": "Ramadhan", "Waktu Akses     :": "2024-04-15 12:01:56"}, {"Judul Berita    :": "Marquez Ungkap Ada Masalah yang Sebabkan Dirinya Jatuh dan Relakan Posisi Terdepan", "Waktu Publish   :": "3 jam yang lalu", "Kategori        :": "Sport", "Waktu Akses     :": "2024-04-15 12:01:56"}, {"Judul Berita    :": "Agar Doa Terkabul", "Waktu Publish   :": "3 jam yang lalu", "Kategori        :": "Video", "Waktu Akses     :": "2024-04-15 12:01:56"}, {"Judul Berita    :": "Jungkook Bikin Akun Instagram Baru, Sudah Diikuti 2,7 Juta Orang, Sudah Follow?", "Waktu Publish   :": "3 jam yang lalu", "Kategori        :": "Ameera", "Waktu Akses     :": "2024-04-15 12:01:56"}, {"Judul Berita    :": "Demokrat: SBY-Prabowo di Cikeas Jadi Pertemuan yang Dahsyat", "Waktu Publish   :": "3 jam yang lalu", "Kategori        :": "News", "Waktu Akses     :": "2024-04-15 12:01:56"}, {"Judul Berita    :": "Gubernur Sumbar: Kendaraan Jangan Berhenti di Flyover Kelok Sembilan", "Waktu Publish   :": "3 jam yang lalu", "Kategori        :": "Ramadhan", "Waktu Akses     :": "2024-04-15 12:01:56"}, {"Judul Berita    :": "Ini Prospek Kerja Kreatif untuk Lulusan Hukum Bisnis", "Waktu Publish   :": "3 jam yang lalu", "Kategori        :": "News", "Waktu Akses     :": "2024-04-15 12:01:56"}, {"Judul Berita    :": "Sebanyak 14 Orang Meninggal Akibat Tanah Longsor di Tana Toraja", "Waktu Publish   :": "3 jam yang lalu", "Kategori        :": "Network", "Waktu Akses     :": "2024-04-15 12:01:56"}, {"Judul Berita    :": "Cek Kesehatan dan Kelola Stres Jadi Cara Jaga Tubuh Sehat Usai Lebaran", "Waktu Publish   :": "3 jam yang lalu", "Kategori        :": "Ameera", "Waktu Akses     :": "2024-04-15 12:01:56"}, {"Judul Berita    :": "Sejak Lebaran, Lebih dari 100 Ribu Kendaraan Keluar dari Tol Pasteur", "Waktu Publish   :": "3 jam yang lalu", "Kategori        :": "Ramadhan", "Waktu Akses     :": "2024-04-15 12:01:56"}, {"Judul Berita    :": "Kendaraan dari Arah Jakarta Melalui Cirebon Masih Meningkat Setelah Lebaran", "Waktu Publish   :": "3 jam yang lalu", "Kategori        :": "News", "Waktu Akses     :": "2024-04-15 12:01:56"}, {"Judul Berita    :": "BRIN Dorong Pengembangan Kebun Raya Daerah untuk Konservasi Tumbuhan", "Waktu Publish   :": "3 jam yang lalu", "Kategori        :": "Esgnow", "Waktu Akses     :": "2024-04-15 12:01:56"}, {"Judul Berita    :": "Pengamanan Selama Arus Balik, Polisi Patroli Malam di Yogyakarta", "Waktu Publish   :": "3 jam yang lalu", "Kategori        :": "Ramadhan", "Waktu Akses     :": "2024-04-15 12:01:56"}, {"Judul Berita    :": "Pemeriksaan Genomik di Dalam Negeri Lindungi Data Gen Individu", "Waktu Publish   :": "4 jam yang lalu", "Kategori        :": "Tekno", "Waktu Akses     :": "2024-04-15 12:01:56"}, {"Judul Berita    :": "Rekor Baru! Reaktor Matahari Buatan di Korea Selatan Tembus Suhu 100 Juta Derajat Celcius!", "Waktu Publish   :": "4 jam yang lalu", "Kategori        :": "Network", "Waktu Akses     :": "2024-04-15 12:01:56"}, {"Judul Berita    :": "Polisi Amankan Arus Balik di Stasiun Yogyakarta", "Waktu Publish   :": "4 jam yang lalu", "Kategori        :": "Ramadhan", "Waktu Akses     :": "2024-04-15 12:01:56"}, {"Judul Berita    :": "Penumpang LRT Sumatra Selatan Capai 188.481 Orang Saat Libur Idul Fitri", "Waktu Publish   :": "4 jam yang lalu", "Kategori        :": "News", "Waktu Akses     :": "2024-04-15 12:01:56"}, {"Judul Berita    :": "FKUI: Penanganan Cedera Olahraga Holistik Penting untuk Performa Atlet", "Waktu Publish   :": "4 jam yang lalu", "Kategori        :": "Ameera", "Waktu Akses     :": "2024-04-15 12:01:56"}, {"Judul Berita    :": "UNM Tawarkan Biaya Kuliah Terjangkau dan Berkualitas", "Waktu Publish   :": "4 jam yang lalu", "Kategori        :": "News", "Waktu Akses     :": "2024-04-15 12:01:56"}, {"Judul Berita    :": "Guru Kakek Sultan Agung Meninggal, Lebih dari 20 Tahun Kemudian Menampakkan Diri di Depan Sultan Agung", "Waktu Publish   :": "4 jam yang lalu", "Kategori        :": "Network", "Waktu Akses     :": "2024-04-15 12:01:56"}]